{
    "module": "v-realonlyForm-btn",
    "layout": {
        "form": {
            "scope": "formData",
            "initRequest": "${{params}}",
            "btns": [
               
            ],
            "controls": [
                {
                    "lmt_ccy_rule": {
                        "control": "string",
                        "label": "额度币种规则",
                        "dict": {
                            "dictType": "LN_E_LMT_CCY_RULE",
                            "dictKey": [
                                "LN_E_LMT_CCY_RULE"
                            ],
                            "format": "label"
                        },
                        "width": "130px"
                    },
                    "lmt_asgn_ccy": {
                        "control": "string",
                        "label": "额度指定币种",
                        "width": "130px"
                    }
                },
                {
                    "lmt_use_rule": {
                        "control": "string",
                        "label": "额度使用规则",
                        "dict": {
                            "dictType": "LN_E_LMT_USE_RULE",
                            "dictKey": [
                                "LN_E_LMT_USE_RULE"
                            ],
                            "format": "label"
                        },
                        "width": "130px"
                    }
                }
                
            ]
        }
    }
}