{
  "module": "v-cardList4",
  "layout": {
      "card": {
          "span": {
              "xs": 24,
              "sm": 24,
              "md": 24,
              "lg": 24,
              "xl": 24
          },
          "list": [
              {
                  "label": "整体流量",
                  "toRequest": {
                      "url": "/views/risk/risk_monitor_management/risk_traffic_info/risk_overall_traffic.json",
                      "method": "get",
                      "params": {}
                  },
                  "params": {},
                  "closable": false
              },
              {
                  "label": "流量趋势",
                  "toRequest": {
                      "url": "@riskTrafficTrend",
                      "method": "get",
                      "params": {}
                  },
                  "params": {},
                  "closable": false,
                  "btns": [
                  ]
              },
              {
                  "label": "实时流量",
                  "toRequest": {
                      "url": "@riskRealTimeTraffic",
                      "method": "get",
                      "params": {}
                  },
                  "params": {},
                  "closable": false,
                  "btns": [
                  ]
              }
          ]
      }
  }
}