{
  "module": "v_search_btn_datagrid",
  "layout": {
    "datagrid": {
      "scope": "searchTable",
      "isInitSearch": false,
      "doRequest": {
        "url": "/SUMP/icmcall/icmRPCCall",
        "method": "POST",
        "params": {
          "servicecode": "syln0021",
          "adv_rpymt_fine_num":"${{params.adv_rpymt_fine_num}}",
          "outlistid": "list01"
        }
      },
      "thead": [
        {
          "align": "center",
          "label": "提前还款罚金编号",
          "prop": "adv_rpymt_fine_num"
        },
        {
          "align": "center",
          "label": "数值序号",
          "prop": "numrcl_val_serl_num"
        },
        {
          "align": "center",
          "label": "期限/百分比", 
          "prop": "matu_pcnt"
        },
        {
          "align": "center",
          "label": "提前还款罚金基数",
          "prop": "adv_rpymt_fine_base_num",
          "dict": {
            "dictType": "LN_E_ADV_RPYMT_FINE_BASE_NUM",
            "dictKey": [
              "LN_E_ADV_RPYMT_FINE_BASE_NUM"
            ],
            "format": "label"
          }
        },
        {
          "align": "center",
          "label": "罚金计算方法",
          "prop": "fine_caln_meth",
          "dict": {
            "dictType": "LN_E_FINE_CALN_METH",
            "dictKey": [
              "LN_E_FINE_CALN_METH"
            ],
            "format": "label"
          }
        },
        {
          "align": "center",
          "label": "罚金金额/百分比",
          "prop": "fine_amt_pcnt"
        }
      ]
    }
  }
}