{
  "module": "v-form-btn-dynamic",
 "layout": {
   "form": {
     "initRequest":"${{params}}",
     "controlsGroup": [
       {
         "title": "分期信息",
         "tooltip": "step1",
         "titleIcon": "",
         "showHint": "",
         "accordion": false,
         "expand": true,
         "controls": [
           {
             "id1": {
               "control": "dynamic",
               "span": 24,
               "toRequest": {
                 "url": "/views/lxyk/xyf/flow/credit_card_order_bystages_info.json",
                 "method": "post",
                 "params": {
                   "apply_no":"${{params.apply_no}}",
                   "pageType":"detail"
                 }
               }
             }
           }
         ]
       }
     ]
   }
 }
}
