{
  "module": "v_inputDataForm_btn",
  "layout": {
    "form": {
      "controls": [
        {
          "cortno": {
            "control": "select",
            "label": "业务限额详情",
            "width": "100px",
            "rules": [
              {
                "required": true,
                "message": "业务限额类型"
              }
            ],

            "dict": {
              "dictType": "E_LIMIT",
              "dictKey": [
                "E_LIMIT"
              ],
              "format": "label"
            }
          }

        }

      ]
    }
  }
}
